crkaf/__init__.py
crkaf-1.1.dist-info/METADATA
crkaf-1.1.dist-info/WHEEL
crkaf-1.1.dist-info/entry_points.txt
crkaf-1.1.dist-info/top_level.txt
crkaf-1.1.dist-info/RECORD
